mypackage/__init__.py
mypackage/mymodule.py
tests/__init__.py
tests/test_mymodule.py
cmiron_package-0.1.0.dist-info/LICENSE
cmiron_package-0.1.0.dist-info/METADATA
cmiron_package-0.1.0.dist-info/WHEEL
cmiron_package-0.1.0.dist-info/top_level.txt
cmiron_package-0.1.0.dist-info/RECORD
